ovirtansible
